{
    "type": "object",
    "properties": {
        "bitmap_type": {
            "type": "string",
            "enum": ["jpg", "png"]
        },
        "bitmap_data": {
            "type": "string",
            "format": "base64"
        },
        "location": {
            "$ref": "location.json"
        },
        "normal": {
            "type": "object",
            "properties": {
                "x": {
                    "type": "number"
                },
                "y": {
                    "type": "number"
                },
                "z": {
                    "type": "number"
                }
            }
        },
        "up": {
            "type": "object",
            "properties": {
                "x": {
                    "type": "number"
                },
                "y": {
                    "type": "number"
                },
                "z": {
                    "type": "number"
                }
            }
        },
        "height": {
            "type": "number"
        }
    }
}
