{
"$schema": "http://json-schema.org/draft-03/schema#", 
  "title": "topic_POST",
 "description": "Schema for topic POST, BCF REST API.",
  "type": "object",
  "properties": {
    "topic_type": {
      "type": [
        "string",
        "null"
      ]
    },
    "topic_status": {
      "type": [
        "string",
        "null"
      ]
    },
    "reference_links": {
      "type": [
        "array",
        "null"
      ],
      "items": {
        "type": "string"
      }
    },
    "title": {
      "required": true,
      "type": "string"
    },
    "priority": {
      "type": [
        "string",
        "null"
      ]
    },
    "index": {
      "type": "integer"
    },
    "labels": {
      "type": [
        "array",
        "null"
      ],
      "items": {
        "type": [
          "string",
          "null"
        ]
      }
    },
    "assigned_to": {
      "type": [
        "string",
        "null"
      ]
    },
    "description": {
      "type": [
        "string",
        "null"
      ]
    },
    "bim_snippet": {
      "title": "bim_snippet",
      "type": [
        "object",
        "null"
      ],
      "properties": {
        "snippet_type": {
          "required": true,
          "type": "string"
        },
        "is_external": {
          "required": true,
          "type": "boolean"
        },
        "reference": {
          "required": true,
          "type": "string"
        },
        "reference_schema": {
          "required": true,
          "type": "string"
        }
      }
    },
	"due_date": {
	  "type": [
	    "string",
		"null"
	  ]
	}
  }
}